jobbergate_cli/__init__.py
jobbergate_cli/application_base.py
jobbergate_cli/auth.py
jobbergate_cli/compat.py
jobbergate_cli/config.py
jobbergate_cli/constants.py
jobbergate_cli/context.py
jobbergate_cli/exceptions.py
jobbergate_cli/jobberappslib.py
jobbergate_cli/logging.py
jobbergate_cli/main.py
jobbergate_cli/render.py
jobbergate_cli/requests.py
jobbergate_cli/schemas.py
jobbergate_cli/subapps/__init__.py
jobbergate_cli/subapps/applications/__init__.py
jobbergate_cli/subapps/applications/app.py
jobbergate_cli/subapps/applications/application_base.py
jobbergate_cli/subapps/applications/application_helpers.py
jobbergate_cli/subapps/applications/questions.py
jobbergate_cli/subapps/applications/tools.py
jobbergate_cli/subapps/clusters/__init__.py
jobbergate_cli/subapps/clusters/app.py
jobbergate_cli/subapps/clusters/tools.py
jobbergate_cli/subapps/job_scripts/__init__.py
jobbergate_cli/subapps/job_scripts/app.py
jobbergate_cli/subapps/job_scripts/tools.py
jobbergate_cli/subapps/job_submissions/__init__.py
jobbergate_cli/subapps/job_submissions/app.py
jobbergate_cli/subapps/job_submissions/tools.py
jobbergate_cli/subapps/pagination.py
jobbergate_cli/subapps/tools.py
jobbergate_cli/text_tools.py
jobbergate_cli-5.9.0.dist-info/LICENSE
jobbergate_cli-5.9.0.dist-info/METADATA
jobbergate_cli-5.9.0.dist-info/WHEEL
jobbergate_cli-5.9.0.dist-info/entry_points.txt
jobbergate_cli-5.9.0.dist-info/RECORD
