Metadata-Version: 2.1
Name: jobbergate-cli
Version: 5.9.0
Summary: Jobbergate CLI Client
Home-page: https://github.com/omnivector-solutions/jobbergate
License: MIT
Author: Omnivector Solutions
Author-email: info@omnivector.solutions
Requires-Python: >=3.10,<4.0
Classifier: Development Status :: 5 - Production/Stable
Classifier: License :: OSI Approved :: MIT License
Classifier: Operating System :: OS Independent
Classifier: Programming Language :: Python :: 3
Classifier: Programming Language :: Python :: 3.10
Classifier: Programming Language :: Python :: 3.11
Classifier: Topic :: Scientific/Engineering
Requires-Dist: Jinja2 (>=3.1.6,<4.0.0)
Requires-Dist: PyYAML (>=6.0.3,<7.0.0)
Requires-Dist: click (>=8.3.1,<9.0.0)
Requires-Dist: importlib-metadata (>=8.7.0,<9.0.0)
Requires-Dist: inquirer (>=3.4.1,<4.0.0)
Requires-Dist: jobbergate-core (==5.9.0)
Requires-Dist: pydantic-settings (>=2.12.0,<3.0.0)
Requires-Dist: pyperclip (>=1.11.0,<2.0.0)
Requires-Dist: python-dotenv (>=1.2.1,<2.0.0)
Requires-Dist: rich (>=14.2.0,<15.0.0)
Requires-Dist: sentry-sdk (>=2.47.0,<3.0.0)
Requires-Dist: typer (>=0.20.0,<0.21.0)
Project-URL: Bug Tracker, https://github.com/omnivector-solutions/jobbergate/issues
Project-URL: Changelog, https://github.com/omnivector-solutions/jobbergate/blob/main/jobbergate-cli/CHANGELOG.rst
Project-URL: Repository, https://github.com/omnivector-solutions/jobbergate
